{
  "generated_at": "2026-03-25 03:48 UTC",
  "repo_languages": [
    {
      "language": "C",
      "lines": 53534
    },
    {
      "language": "Sage",
      "lines": 52558
    },
    {
      "language": "JSON",
      "lines": 4703
    },
    {
      "language": "Shell",
      "lines": 893
    },
    {
      "language": "Makefile",
      "lines": 718
    },
    {
      "language": "CMake",
      "lines": 431
    },
    {
      "language": "Dockerfile",
      "lines": 41
    }
  ],
  "compiler_comparison": [
    {
      "label": "Self-Hosted Sage Core",
      "lines": 10794
    },
    {
      "label": "Native C Core",
      "lines": 50958
    }
  ],
  "recipe_benchmark": {
    "workload": "benchmarks/runtime_compare.sage",
    "runs": 5,
    "warmups": 1,
    "checksum": "11520",
    "results": [
      {
        "name": "sage-interpreted-c-ast",
        "label": "Interpreted (C + AST)",
        "status": "ok",
        "reason": "",
        "output": "11520",
        "build_median_seconds": 0.0,
        "run_median_seconds": 0.007776448968797922,
        "total_median_seconds": 0.007776448968797922,
        "build_mean_seconds": 0.0,
        "run_mean_seconds": 0.0075835083960555496,
        "total_mean_seconds": 0.0075835083960555496
      },
      {
        "name": "sage-interpreted-vm",
        "label": "Interpreted (VM)",
        "status": "ok",
        "reason": "",
        "output": "11520",
        "build_median_seconds": 0.0,
        "run_median_seconds": 0.007274125004187226,
        "total_median_seconds": 0.007274125004187226,
        "build_mean_seconds": 0.0,
        "run_mean_seconds": 0.007385137816891074,
        "total_mean_seconds": 0.007385137816891074
      },
      {
        "name": "sage-compiled-c",
        "label": "Compiled (C)",
        "status": "ok",
        "reason": "",
        "output": "11520",
        "build_median_seconds": 0.12010289600584656,
        "run_median_seconds": 0.0015777419903315604,
        "total_median_seconds": 0.12152674503158778,
        "build_mean_seconds": 0.11980325459735468,
        "run_mean_seconds": 0.0015345062129199505,
        "total_mean_seconds": 0.12133776081027463
      },
      {
        "name": "sage-compiled-vm",
        "label": "Compiled (VM)",
        "status": "ok",
        "reason": "",
        "output": "11520",
        "build_median_seconds": 0.004121339006815106,
        "run_median_seconds": 0.006394131982233375,
        "total_median_seconds": 0.010661879030521959,
        "build_mean_seconds": 0.0040349907940253615,
        "run_mean_seconds": 0.006677911395672709,
        "total_mean_seconds": 0.01071290218969807
      },
      {
        "name": "sage-compiled-sage",
        "label": "Compiled (Sage)",
        "status": "failed",
        "reason": "checksum mismatch: expected '11520', got ''",
        "output": "",
        "build_median_seconds": 0.09376371692633256,
        "run_median_seconds": 0.0008427479770034552,
        "total_median_seconds": 0.09442796895746142,
        "build_mean_seconds": 0.09458652818575501,
        "run_mean_seconds": 0.0007989239995367825,
        "total_mean_seconds": 0.09538545218529179
      }
    ]
  }
}
