{
  "generated_at": "2026-04-05 17:01 UTC",
  "repo_languages": [
    {
      "language": "Sage",
      "lines": 71808
    },
    {
      "language": "C",
      "lines": 59678
    },
    {
      "language": "JSON",
      "lines": 4729
    },
    {
      "language": "Shell",
      "lines": 1406
    },
    {
      "language": "Makefile",
      "lines": 799
    },
    {
      "language": "CMake",
      "lines": 499
    },
    {
      "language": "Dockerfile",
      "lines": 41
    }
  ],
  "compiler_comparison": [
    {
      "label": "Self-Hosted Sage Core",
      "lines": 11583
    },
    {
      "label": "Native C Core",
      "lines": 57018
    }
  ],
  "recipe_benchmark": {
    "workload": "benchmarks/runtime_compare.sage",
    "runs": 5,
    "warmups": 1,
    "checksum": "421782618",
    "results": [
      {
        "name": "sage-interpreted-c-ast",
        "label": "Interpreted (C + AST)",
        "status": "ok",
        "reason": "",
        "output": "421782618",
        "build_median_seconds": 0.0,
        "run_median_seconds": 0.008179824988474138,
        "total_median_seconds": 0.008179824988474138,
        "build_mean_seconds": 0.0,
        "run_mean_seconds": 0.0073852624016581105,
        "total_mean_seconds": 0.0073852624016581105
      },
      {
        "name": "sage-interpreted-vm",
        "label": "Interpreted (VM)",
        "status": "ok",
        "reason": "",
        "output": "421782618",
        "build_median_seconds": 0.0,
        "run_median_seconds": 0.007033606991171837,
        "total_median_seconds": 0.007033606991171837,
        "build_mean_seconds": 0.0,
        "run_mean_seconds": 0.006853692998993211,
        "total_mean_seconds": 0.006853692998993211
      },
      {
        "name": "sage-compiled-c",
        "label": "Compiled (C)",
        "status": "failed",
        "reason": "checksum mismatch: expected '421782618', got '4.21783e+08'",
        "output": "4.21783e+08",
        "build_median_seconds": 0.12366489499981981,
        "run_median_seconds": 0.0016759319987613708,
        "total_median_seconds": 0.1255237169971224,
        "build_mean_seconds": 0.12222110360453371,
        "run_mean_seconds": 0.001690735001466237,
        "total_mean_seconds": 0.12391183860599994
      },
      {
        "name": "sage-compiled-vm",
        "label": "Compiled (VM)",
        "status": "failed",
        "reason": "checksum mismatch: expected '421782618', got '11520'",
        "output": "11520",
        "build_median_seconds": 0.004301016000681557,
        "run_median_seconds": 0.007181758992373943,
        "total_median_seconds": 0.0114827749930555,
        "build_mean_seconds": 0.0043622924014925955,
        "run_mean_seconds": 0.006644812802551314,
        "total_mean_seconds": 0.01100710520404391
      },
      {
        "name": "sage-compiled-sage",
        "label": "Compiled (Sage)",
        "status": "failed",
        "reason": "build step failed\ncommand: /home/kraken/Devel/sagelang/sage sage.sage --emit-c /home/kraken/Devel/sagelang/benchmarks/runtime_compare.sage -o /home/kraken/Devel/sagelang/.tmp/sage-compiled-sage-aotlgl6f/recipe-compiled-sage.c\ncwd: /home/kraken/Devel/sagelang/src/sage\nstderr:\nerror: expected property name after '.' or '->'\n  --> ./pass.sage:62:96\n   |\n62 |         return ast.slice_expr(clone_expr(expr.object), clone_expr(expr.start), clone_expr(expr.end))\n   |                                                                                                ~~~\n  = help: identifiers start with a letter or '_'",
        "output": null,
        "build_median_seconds": null,
        "run_median_seconds": null,
        "total_median_seconds": null,
        "build_mean_seconds": null,
        "run_mean_seconds": null,
        "total_mean_seconds": null
      },
      {
        "name": "sage-jit",
        "label": "sage-jit",
        "status": "ok",
        "reason": "",
        "output": "421782618",
        "build_median_seconds": 0.0,
        "run_median_seconds": 0.006833637002273463,
        "total_median_seconds": 0.006833637002273463,
        "build_mean_seconds": 0.0,
        "run_mean_seconds": 0.0069369502045447005,
        "total_mean_seconds": 0.0069369502045447005
      },
      {
        "name": "sage-aot",
        "label": "sage-aot",
        "status": "failed",
        "reason": "checksum mismatch: expected '421782618', got 'inf'",
        "output": "inf",
        "build_median_seconds": 0.04770074499538168,
        "run_median_seconds": 0.0007725439936621115,
        "total_median_seconds": 0.04843926698958967,
        "build_mean_seconds": 0.047674298597848976,
        "run_mean_seconds": 0.0008014559978619217,
        "total_mean_seconds": 0.04847575459571089
      }
    ]
  }
}
